{
"autoplayBgm":false,"autoplayBgs":false,"battleback1Name":"Wood1","battleback2Name":"Room2","bgm":{"name":"277447_shadydave_alone","pan":0,"pitch":100,"volume":70},"bgs":{"name":"","pan":0,"pitch":100,"volume":80},"disableDashing":false,"displayName":"","encounterList":[],"encounterStep":30,"height":20,"note":"","parallaxLoopX":false,"parallaxLoopY":false,"parallaxName":"","parallaxShow":false,"parallaxSx":0,"parallaxSy":0,"scrollType":0,"specifyBattleback":false,"tilesetId":16,"width":7,
"data":[4116,4140,4140,4140,4140,4140,4120,4136,6835,6833,6833,6833,6837,4128,4136,6832,2850,2836,2852,6832,4128,4136,6832,2832,2816,2840,6832,4128,4136,6832,2832,2816,2840,6832,4128,4136,6832,2832,2816,2840,6832,4128,4136,6832,2832,2816,2840,6832,4128,4136,6832,2832,2816,2840,6832,4128,4136,6832,2832,2816,2840,6832,4128,4136,6832,2832,2816,2840,6832,4128,4136,6832,2832,2816,2840,6832,4128,4136,6832,2832,2816,2840,6832,4128,4136,6832,2832,2816,2840,6832,4128,4136,6832,2832,2816,2840,6832,4128,4136,6832,2832,2816,2840,6832,4128,4136,6832,2832,2816,2840,6832,4128,4136,6832,2832,2816,2840,6832,4128,4136,6844,2856,2844,2854,6844,4128,4114,4132,4132,4132,4132,4132,4113,4112,4112,4112,4112,4112,4112,4112,0,0,0,0,0,0,0,0,4195,4193,4193,4193,4197,0,0,4192,0,0,0,4192,0,0,4192,0,0,0,4192,0,0,4192,0,0,0,4192,0,0,4192,0,0,0,4192,0,0,4192,0,0,0,4192,0,0,4192,0,0,0,4204,0,0,4192,0,0,0,0,0,0,4192,0,0,0,0,0,0,4192,0,0,0,4202,0,0,4192,0,0,0,4192,0,0,4192,0,0,0,4192,0,0,4192,0,0,0,4192,0,0,4192,0,0,0,4192,0,0,4192,0,0,0,4192,0,0,4204,0,0,0,4192,0,0,0,0,0,0,4204,0,0,0,0,0,0,0,0,0,0,0,0,0,0,0,0,0,0,0,0,0,0,0,0,0,0,0,0,0,0,0,0,0,0,0,0,0,0,0,0,0,0,0,0,0,0,0,0,0,0,0,0,0,0,0,0,0,0,0,0,0,0,0,0,0,0,0,0,0,0,0,0,0,0,0,0,0,0,0,0,0,0,0,0,0,0,0,0,0,0,0,0,0,0,0,0,0,0,0,0,0,0,0,0,0,0,0,0,0,0,0,0,0,0,0,0,0,0,0,0,0,0,0,0,0,0,0,0,0,0,0,0,0,0,0,0,0,0,0,0,0,0,0,0,0,0,0,0,0,0,0,0,0,0,0,0,0,0,0,0,0,0,0,0,0,0,0,0,0,0,0,0,0,0,0,0,0,0,0,0,0,0,0,0,0,0,0,0,0,0,0,0,0,0,0,0,0,0,0,0,0,0,0,0,0,0,0,0,0,0,0,0,0,0,0,0,0,0,0,0,0,0,0,0,0,0,0,0,0,0,0,0,0,0,0,0,0,0,0,0,0,0,0,0,0,0,0,0,0,0,0,0,0,0,0,0,0,0,0,0,0,0,0,0,0,0,0,0,0,0,0,0,0,0,0,0,0,0,0,0,0,0,0,0,0,0,0,0,0,0,0,0,0,0,0,0,0,0,0,0,0,0,0,0,0,0,0,0,0,0,0,5,0,0,0,5,0,0,5,0,0,0,5,0,0,5,0,0,0,5,0,0,5,0,0,0,5,0,0,5,0,0,0,5,0,0,5,0,0,0,5,0,0,5,0,0,0,5,0,0,5,0,0,0,5,0,0,5,0,0,0,5,0,0,5,0,0,0,5,0,0,5,0,0,0,5,0,0,5,0,0,0,5,0,0,5,0,0,0,5,0,0,5,0,0,0,5,0,0,5,0,0,0,5,0,0,5,0,0,0,5,0,0,0,0,0,0,0,0,0,0,0,0,0,0,0,0,0,0,0,0,0,0,0,0,0,0,0,0,0,0,0,0,0,0,0,0,0,0,0,0,0,0,0,0,0,0,0,0,0,0,0,0,0,0,0,0,0,0,0,0,0,0,0,0,0,0,0,0,0,0,0,0,0,0,0,0,0,0,0,0,0,0,0,0,0,0,0,0,0,0,0,0,0,0,0,0,0,0,0,0,0,0,0,0,0,0,0,0,0,0,0,0,0,0,0,0,0,0,0,0,0,0,0,0,0,0,0,0,0,0,0,0,0,0,0,0,0,0,0,0,0,0,0,0,0,0,0,0,0,0,0,0,0,0],
"events":[
null,
{"id":1,"name":"EV001","note":"","pages":[{"conditions":{"actorId":1,"actorValid":false,"itemId":1,"itemValid":false,"selfSwitchCh":"A","selfSwitchValid":false,"switch1Id":1,"switch1Valid":false,"switch2Id":1,"switch2Valid":false,"variableId":1,"variableValid":false,"variableValue":0},"directionFix":true,"image":{"tileId":0,"characterName":"!$pictures","direction":4,"pattern":0,"characterIndex":0},"list":[{"code":108,"indent":0,"parameters":["<mv3d:shape(fence),z(-0.3),x(-0.55),scale(2.2,2.2),rot(90),y(0.59),shadow(false)>"]},{"code":0,"indent":0,"parameters":[]}],"moveFrequency":3,"moveRoute":{"list":[{"code":0,"parameters":[]}],"repeat":true,"skippable":false,"wait":false},"moveSpeed":3,"moveType":0,"priorityType":0,"stepAnime":false,"through":false,"trigger":0,"walkAnime":false}],"x":5,"y":11},
{"id":2,"name":"EV002","note":"<mv3d:scale(1.7)>","pages":[{"conditions":{"actorId":1,"actorValid":false,"itemId":1,"itemValid":false,"selfSwitchCh":"A","selfSwitchValid":false,"switch1Id":1,"switch1Valid":false,"switch2Id":1,"switch2Valid":false,"variableId":1,"variableValid":false,"variableValue":0},"directionFix":false,"image":{"characterIndex":0,"characterName":"","direction":2,"pattern":0,"tileId":0},"list":[{"code":0,"indent":0,"parameters":[]}],"moveFrequency":3,"moveRoute":{"list":[{"code":0,"parameters":[]}],"repeat":true,"skippable":false,"wait":false},"moveSpeed":3,"moveType":0,"priorityType":0,"stepAnime":false,"through":false,"trigger":0,"walkAnime":true},{"conditions":{"actorId":1,"actorValid":false,"itemId":1,"itemValid":false,"selfSwitchCh":"A","selfSwitchValid":false,"switch1Id":297,"switch1Valid":true,"switch2Id":1,"switch2Valid":false,"variableId":1,"variableValid":false,"variableValue":0},"directionFix":false,"image":{"tileId":0,"characterName":"$Nanami","direction":2,"pattern":1,"characterIndex":0},"list":[{"code":108,"indent":0,"parameters":["<mv3d:"]},{"code":408,"indent":0,"parameters":["lamp(white,1,0.8)"]},{"code":408,"indent":0,"parameters":[">"]},{"code":108,"indent":0,"parameters":["<mv3d:shadow(0)>"]},{"code":0,"indent":0,"parameters":[]}],"moveFrequency":5,"moveRoute":{"list":[{"code":1,"indent":null},{"code":1,"indent":null},{"code":0,"parameters":[]}],"repeat":false,"skippable":false,"wait":false},"moveSpeed":4,"moveType":3,"priorityType":1,"stepAnime":false,"through":false,"trigger":0,"walkAnime":true}],"x":3,"y":5},
{"id":3,"name":"EV003","note":"<mv3d:shape(fence),z(0),y(-0.50),x(-0.53),yaw(90),scale(1,1.1),shadow(false)>","pages":[{"conditions":{"actorId":1,"actorValid":false,"itemId":1,"itemValid":false,"selfSwitchCh":"B","selfSwitchValid":false,"switch1Id":1,"switch1Valid":false,"switch2Id":1,"switch2Valid":false,"variableId":1,"variableValid":false,"variableValue":0},"directionFix":true,"image":{"tileId":0,"characterName":"!$locker1","direction":6,"pattern":0,"characterIndex":0},"list":[{"code":250,"indent":0,"parameters":[{"name":"Open5","volume":35,"pitch":130,"pan":0}]},{"code":221,"indent":0,"parameters":[]},{"code":201,"indent":0,"parameters":[0,132,1,5,6,0]},{"code":205,"indent":0,"parameters":[-1,{"list":[{"code":41,"parameters":["$Yuma",0],"indent":null},{"code":0}],"repeat":false,"skippable":false,"wait":false}]},{"code":505,"indent":0,"parameters":[{"code":41,"parameters":["$Yuma",0],"indent":null}]},{"code":356,"indent":0,"parameters":["mv3d cameraMode orthographic"]},{"code":356,"indent":0,"parameters":["mv3d camera target ＠e66 0"]},{"code":356,"indent":0,"parameters":["mv3d sun pitch 180 0"]},{"code":356,"indent":0,"parameters":["mv3d fog black 8 11 0"]},{"code":356,"indent":0,"parameters":["mv3d ambient #1B0A2A 0"]},{"code":356,"indent":0,"parameters":["mv3d yaw 8 0"]},{"code":356,"indent":0,"parameters":["mv3d dist 7 0"]},{"code":230,"indent":0,"parameters":[40]},{"code":222,"indent":0,"parameters":[]},{"code":0,"indent":0,"parameters":[]}],"moveFrequency":3,"moveRoute":{"list":[{"code":0,"parameters":[]}],"repeat":true,"skippable":false,"wait":false},"moveSpeed":3,"moveType":0,"priorityType":1,"stepAnime":false,"through":false,"trigger":0,"walkAnime":false}],"x":5,"y":15},
{"id":4,"name":"EV004","note":"","pages":[{"conditions":{"actorId":1,"actorValid":false,"itemId":1,"itemValid":false,"selfSwitchCh":"A","selfSwitchValid":false,"switch1Id":1,"switch1Valid":false,"switch2Id":1,"switch2Valid":false,"variableId":1,"variableValid":false,"variableValue":0},"directionFix":false,"image":{"characterIndex":0,"characterName":"","direction":2,"pattern":0,"tileId":0},"list":[{"code":108,"indent":0,"parameters":["<mv3d:"]},{"code":408,"indent":0,"parameters":["lamp(white,1.5,3)"]},{"code":408,"indent":0,"parameters":["lampHeight(0)"]},{"code":408,"indent":0,"parameters":[">"]},{"code":0,"indent":0,"parameters":[]}],"moveFrequency":3,"moveRoute":{"list":[{"code":0,"parameters":[]}],"repeat":true,"skippable":false,"wait":false},"moveSpeed":3,"moveType":0,"priorityType":0,"stepAnime":false,"through":false,"trigger":0,"walkAnime":true}],"x":3,"y":15},
{"id":5,"name":"EV005","note":"<mv3d:shape(fence),z(0),y(-0.50),x(0.51),yaw(90),scale(1,1.1),shadow(false)>","pages":[{"conditions":{"actorId":1,"actorValid":false,"itemId":1,"itemValid":false,"selfSwitchCh":"B","selfSwitchValid":false,"switch1Id":1,"switch1Valid":false,"switch2Id":1,"switch2Valid":false,"variableId":1,"variableValid":false,"variableValue":0},"directionFix":true,"image":{"tileId":0,"characterName":"!$locker1","direction":6,"pattern":0,"characterIndex":0},"list":[{"code":250,"indent":0,"parameters":[{"name":"Open5","volume":35,"pitch":130,"pan":0}]},{"code":221,"indent":0,"parameters":[]},{"code":201,"indent":0,"parameters":[0,131,8,5,4,0]},{"code":205,"indent":0,"parameters":[-1,{"list":[{"code":41,"parameters":["$Yuma",0],"indent":null},{"code":0}],"repeat":false,"skippable":false,"wait":false}]},{"code":505,"indent":0,"parameters":[{"code":41,"parameters":["$Yuma",0],"indent":null}]},{"code":356,"indent":0,"parameters":["mv3d cameraMode orthographic"]},{"code":356,"indent":0,"parameters":["mv3d camera target ＠e55 0"]},{"code":356,"indent":0,"parameters":["mv3d fog black 8 11 0"]},{"code":356,"indent":0,"parameters":["mv3d ambient #1B0A2A 0"]},{"code":356,"indent":0,"parameters":["mv3d sun pitch 180 0"]},{"code":356,"indent":0,"parameters":["mv3d yaw -8 0"]},{"code":356,"indent":0,"parameters":["mv3d dist 7 0"]},{"code":230,"indent":0,"parameters":[40]},{"code":222,"indent":0,"parameters":[]},{"code":0,"indent":0,"parameters":[]}],"moveFrequency":3,"moveRoute":{"list":[{"code":0,"parameters":[]}],"repeat":true,"skippable":false,"wait":false},"moveSpeed":3,"moveType":0,"priorityType":1,"stepAnime":false,"through":false,"trigger":0,"walkAnime":false}],"x":1,"y":15},
{"id":6,"name":"EV006","note":"","pages":[{"conditions":{"actorId":1,"actorValid":false,"itemId":1,"itemValid":false,"selfSwitchCh":"A","selfSwitchValid":false,"switch1Id":1,"switch1Valid":false,"switch2Id":1,"switch2Valid":false,"variableId":1,"variableValid":false,"variableValue":0},"directionFix":false,"image":{"tileId":0,"characterName":"","direction":2,"pattern":2,"characterIndex":0},"list":[{"code":0,"indent":0,"parameters":[]}],"moveFrequency":3,"moveRoute":{"list":[{"code":0,"parameters":[]}],"repeat":true,"skippable":false,"wait":false},"moveSpeed":3,"moveType":0,"priorityType":1,"stepAnime":false,"through":false,"trigger":0,"walkAnime":true}],"x":2,"y":17},
{"id":7,"name":"EV007","note":"","pages":[{"conditions":{"actorId":1,"actorValid":false,"itemId":1,"itemValid":false,"selfSwitchCh":"A","selfSwitchValid":false,"switch1Id":1,"switch1Valid":false,"switch2Id":1,"switch2Valid":false,"variableId":1,"variableValid":false,"variableValue":0},"directionFix":false,"image":{"tileId":0,"characterName":"","direction":2,"pattern":2,"characterIndex":0},"list":[{"code":0,"indent":0,"parameters":[]}],"moveFrequency":3,"moveRoute":{"list":[{"code":0,"parameters":[]}],"repeat":true,"skippable":false,"wait":false},"moveSpeed":3,"moveType":0,"priorityType":1,"stepAnime":false,"through":false,"trigger":0,"walkAnime":true}],"x":3,"y":17},
{"id":8,"name":"EV008","note":"","pages":[{"conditions":{"actorId":1,"actorValid":false,"itemId":1,"itemValid":false,"selfSwitchCh":"A","selfSwitchValid":false,"switch1Id":31,"switch1Valid":false,"switch2Id":1,"switch2Valid":false,"variableId":1,"variableValid":false,"variableValue":0},"directionFix":false,"image":{"characterIndex":0,"characterName":"","direction":2,"pattern":0,"tileId":0},"list":[{"code":111,"indent":0,"parameters":[6,-1,8]},{"code":221,"indent":1,"parameters":[]},{"code":201,"indent":1,"parameters":[0,127,3,9,8,2]},{"code":121,"indent":1,"parameters":[297,297,0]},{"code":356,"indent":1,"parameters":["mv3d camera target ＠e2 0"]},{"code":356,"indent":1,"parameters":["mv3d dist 5 0"]},{"code":222,"indent":1,"parameters":[]},{"code":250,"indent":1,"parameters":[{"name":"Rabbit","volume":40,"pitch":90,"pan":-40}]},{"code":356,"indent":1,"parameters":["MSGSE TALK 3"]},{"code":231,"indent":1,"parameters":[1,"Coelhosis",0,0,430,215,65,65,255,0]},{"code":101,"indent":1,"parameters":["",0,1,2]},{"code":401,"indent":1,"parameters":["\\C[6] ???: \\C[0]Booo!"]},{"code":235,"indent":1,"parameters":[1]},{"code":356,"indent":1,"parameters":["MSGSE TALK DEFAULT"]},{"code":356,"indent":1,"parameters":["mv3d camera target ＠player 0"]},{"code":356,"indent":1,"parameters":["mv3d dist 6 0"]},{"code":205,"indent":1,"parameters":[-1,{"list":[{"code":14,"parameters":[0,0],"indent":null},{"code":0}],"repeat":false,"skippable":false,"wait":false}]},{"code":505,"indent":1,"parameters":[{"code":14,"parameters":[0,0],"indent":null}]},{"code":231,"indent":1,"parameters":[2,"Badyuma4",0,0,330,125,80,80,255,0]},{"code":101,"indent":1,"parameters":["",0,1,2]},{"code":401,"indent":1,"parameters":["\\C[8] Yuma: \\C[0]Aaaah!"]},{"code":101,"indent":1,"parameters":["",0,1,2]},{"code":401,"indent":1,"parameters":["\\C[8] Yuma: \\C[0]Mas que merda é essa..."]},{"code":235,"indent":1,"parameters":[2]},{"code":230,"indent":1,"parameters":[40]},{"code":356,"indent":1,"parameters":["hide_all_indicators"]},{"code":201,"indent":1,"parameters":[0,127,3,10,8,2]},{"code":356,"indent":1,"parameters":["mv3d yaw 0 0"]},{"code":356,"indent":1,"parameters":["mv3d camera target ＠e2 0"]},{"code":356,"indent":1,"parameters":["mv3d dist 4 0"]},{"code":356,"indent":1,"parameters":["mv3d height 0.7 0"]},{"code":241,"indent":1,"parameters":[{"name":"musicairma","volume":10,"pitch":70,"pan":0}]},{"code":356,"indent":1,"parameters":["MSGSE TALK 3"]},{"code":231,"indent":1,"parameters":[1,"Coelhosis",0,0,430,215,65,65,255,0]},{"code":101,"indent":1,"parameters":["",0,1,2]},{"code":401,"indent":1,"parameters":["\\C[6] ???: \\C[0]Assustei você?"]},{"code":235,"indent":1,"parameters":[1]},{"code":230,"indent":1,"parameters":[20]},{"code":231,"indent":1,"parameters":[1,"Coelhosis",0,0,430,215,65,65,255,0]},{"code":101,"indent":1,"parameters":["",0,1,2]},{"code":401,"indent":1,"parameters":["\\C[6] ???: \\C[0]Hahah."]},{"code":235,"indent":1,"parameters":[1]},{"code":230,"indent":1,"parameters":[20]},{"code":231,"indent":1,"parameters":[1,"Coelhosis",0,0,430,215,65,65,255,0]},{"code":101,"indent":1,"parameters":["",0,1,2]},{"code":401,"indent":1,"parameters":["\\C[6] ???: \\C[0]Que bom, \\.essa era a intenção."]},{"code":356,"indent":1,"parameters":["MSGSE TALK DEFAULT"]},{"code":235,"indent":1,"parameters":[1]},{"code":230,"indent":1,"parameters":[50]},{"code":231,"indent":1,"parameters":[2,"Badyuma2",0,0,330,125,80,80,255,0]},{"code":101,"indent":1,"parameters":["",0,1,2]},{"code":401,"indent":1,"parameters":["\\C[8] Yuma: \\C[0]..."]},{"code":235,"indent":1,"parameters":[2]},{"code":230,"indent":1,"parameters":[40]},{"code":231,"indent":1,"parameters":[2,"Badyuma5",0,0,330,125,80,80,255,0]},{"code":101,"indent":1,"parameters":["",0,1,2]},{"code":401,"indent":1,"parameters":["\\C[8] Yuma: \\C[0]Quem... \\.\\.é você...?"]},{"code":235,"indent":1,"parameters":[2]},{"code":230,"indent":1,"parameters":[50]},{"code":356,"indent":1,"parameters":["MSGSE TALK 3"]},{"code":231,"indent":1,"parameters":[3,"Coelhosis",0,0,430,215,65,65,255,0]},{"code":101,"indent":1,"parameters":["",0,1,2]},{"code":401,"indent":1,"parameters":["\\C[6] ???: \\C[0]Ah, \\.desculpe,"]},{"code":101,"indent":1,"parameters":["",0,1,2]},{"code":401,"indent":1,"parameters":["\\C[6] ???: \\C[0]Que falta de educação a minha."]},{"code":235,"indent":1,"parameters":[3]},{"code":230,"indent":1,"parameters":[30]},{"code":231,"indent":1,"parameters":[3,"Coelhosis",0,0,430,215,65,65,255,0]},{"code":101,"indent":1,"parameters":["",0,1,2]},{"code":401,"indent":1,"parameters":["\\C[6] Marisol: \\C[0]Eu me chamo Marisol."]},{"code":235,"indent":1,"parameters":[3]},{"code":230,"indent":1,"parameters":[20]},{"code":231,"indent":1,"parameters":[3,"Coelhosis",0,0,430,215,65,65,255,0]},{"code":101,"indent":1,"parameters":["",0,1,2]},{"code":401,"indent":1,"parameters":["\\C[6] Marisol: \\C[0]Mas pode me chamar de Mari."]},{"code":235,"indent":1,"parameters":[3]},{"code":230,"indent":1,"parameters":[40]},{"code":231,"indent":1,"parameters":[3,"Coelhosis",0,0,430,215,65,65,255,0]},{"code":101,"indent":1,"parameters":["",0,1,2]},{"code":401,"indent":1,"parameters":["\\C[6] Marisol: \\C[0]Lembre desse nome,"]},{"code":101,"indent":1,"parameters":["",0,1,2]},{"code":401,"indent":1,"parameters":["\\C[6] Marisol: \\C[0]Porque é o nome da sua salvadora!"]},{"code":235,"indent":1,"parameters":[3]},{"code":230,"indent":1,"parameters":[60]},{"code":356,"indent":1,"parameters":["MSGSE TALK DEFAULT"]},{"code":231,"indent":1,"parameters":[2,"Badyuma5",0,0,330,125,80,80,255,0]},{"code":101,"indent":1,"parameters":["",0,1,2]},{"code":401,"indent":1,"parameters":["\\C[8] Yuma: \\C[0]Quê...?"]},{"code":235,"indent":1,"parameters":[2]},{"code":230,"indent":1,"parameters":[30]},{"code":231,"indent":1,"parameters":[3,"Coelhosis",0,0,430,215,65,65,255,0]},{"code":101,"indent":1,"parameters":["",0,1,2]},{"code":401,"indent":1,"parameters":["\\C[6] Marisol: \\C[0]Isso mesmo que ouviu,"]},{"code":101,"indent":1,"parameters":["",0,1,2]},{"code":401,"indent":1,"parameters":["\\C[6] Marisol: \\C[0]Eu vim te tirar desse lugar."]},{"code":235,"indent":1,"parameters":[3]},{"code":230,"indent":1,"parameters":[40]},{"code":356,"indent":1,"parameters":["MSGSE TALK 3"]},{"code":231,"indent":1,"parameters":[3,"Coelhosis",0,0,430,215,65,65,255,0]},{"code":101,"indent":1,"parameters":["",0,1,2]},{"code":401,"indent":1,"parameters":["\\C[6] Marisol: \\C[0]Tinha te visto correndo desesperada mais cedo."]},{"code":235,"indent":1,"parameters":[3]},{"code":230,"indent":1,"parameters":[25]},{"code":231,"indent":1,"parameters":[3,"Coelhosis",0,0,430,215,65,65,255,0]},{"code":101,"indent":1,"parameters":["",0,1,2]},{"code":401,"indent":1,"parameters":["\\C[6] Marisol: \\C[0]Que bom que ainda está viva."]},{"code":235,"indent":1,"parameters":[3]},{"code":230,"indent":1,"parameters":[60]},{"code":231,"indent":1,"parameters":[3,"Coelhosis",0,0,430,215,65,65,255,0]},{"code":101,"indent":1,"parameters":["",0,1,2]},{"code":401,"indent":1,"parameters":["\\C[6] Marisol: \\C[0]Eu até enfrentaria aquele bicho,"]},{"code":101,"indent":1,"parameters":["",0,1,2]},{"code":401,"indent":1,"parameters":["\\C[6] Marisol: \\C[0]Mas sabe como é... \\.heh"]},{"code":235,"indent":1,"parameters":[3]},{"code":230,"indent":1,"parameters":[30]},{"code":231,"indent":1,"parameters":[3,"Coelhosis",0,0,430,215,65,65,255,0]},{"code":101,"indent":1,"parameters":["",0,1,2]},{"code":401,"indent":1,"parameters":["\\C[6] Marisol: \\C[0]Odeio aranhas..."]},{"code":235,"indent":1,"parameters":[3]},{"code":230,"indent":1,"parameters":[40]},{"code":356,"indent":1,"parameters":["MSGSE TALK DEFAULT"]},{"code":231,"indent":1,"parameters":[2,"Badyuma5",0,0,330,125,80,80,255,0]},{"code":101,"indent":1,"parameters":["",0,1,2]},{"code":401,"indent":1,"parameters":["\\C[8] Yuma: \\C[0]Do que está falando...?"]},{"code":101,"indent":1,"parameters":["",0,1,2]},{"code":401,"indent":1,"parameters":["\\C[8] Yuma: \\C[0]Eu não te conheço."]},{"code":235,"indent":1,"parameters":[2]},{"code":230,"indent":1,"parameters":[60]},{"code":231,"indent":1,"parameters":[2,"Badyuma5",0,0,330,125,80,80,255,0]},{"code":101,"indent":1,"parameters":["",0,1,2]},{"code":401,"indent":1,"parameters":["\\C[8] Yuma: \\C[0]..."]},{"code":235,"indent":1,"parameters":[2]},{"code":230,"indent":1,"parameters":[30]},{"code":231,"indent":1,"parameters":[2,"Badyuma5",0,0,330,125,80,80,255,0]},{"code":101,"indent":1,"parameters":["",0,1,2]},{"code":401,"indent":1,"parameters":["\\C[8] Yuma: \\C[0]Nem sei porque estou tendo essa conversa..."]},{"code":101,"indent":1,"parameters":["",0,1,2]},{"code":401,"indent":1,"parameters":["\\C[8] Yuma: \\C[0]Você não é real."]},{"code":235,"indent":1,"parameters":[2]},{"code":230,"indent":1,"parameters":[30]},{"code":356,"indent":1,"parameters":["MSGSE TALK 3"]},{"code":231,"indent":1,"parameters":[3,"Coelhosis",0,0,430,215,65,65,255,0]},{"code":101,"indent":1,"parameters":["",0,1,2]},{"code":401,"indent":1,"parameters":["\\C[6] Marisol: \\C[0]Pera, \\.como é?"]},{"code":101,"indent":1,"parameters":["",0,1,2]},{"code":401,"indent":1,"parameters":["\\C[6] Marisol: \\C[0]Eu não sou real? \\.hahah"]},{"code":235,"indent":1,"parameters":[3]},{"code":230,"indent":1,"parameters":[20]},{"code":231,"indent":1,"parameters":[3,"Coelhosis",0,0,430,215,65,65,255,0]},{"code":101,"indent":1,"parameters":["",0,1,2]},{"code":401,"indent":1,"parameters":["\\C[6] Marisol: \\C[0]Aquela mãezona aranha te acertou na cabeça, \\.foi?"]},{"code":235,"indent":1,"parameters":[3]},{"code":230,"indent":1,"parameters":[30]},{"code":356,"indent":1,"parameters":["MSGSE TALK DEFAULT"]},{"code":231,"indent":1,"parameters":[2,"Badyuma5",0,0,330,125,80,80,255,0]},{"code":101,"indent":1,"parameters":["",0,1,2]},{"code":401,"indent":1,"parameters":["\\C[8] Yuma: \\C[0]Esse é um daqueles sonhos que você parece acordado."]},{"code":235,"indent":1,"parameters":[2]},{"code":230,"indent":1,"parameters":[20]},{"code":231,"indent":1,"parameters":[2,"Badyuma5",0,0,330,125,80,80,255,0]},{"code":101,"indent":1,"parameters":["",0,1,2]},{"code":401,"indent":1,"parameters":["\\C[8] Yuma: \\C[0]Não lembro o nome..."]},{"code":235,"indent":1,"parameters":[2]},{"code":230,"indent":1,"parameters":[30]},{"code":231,"indent":1,"parameters":[2,"Badyuma5",0,0,330,125,80,80,255,0]},{"code":101,"indent":1,"parameters":["",0,1,2]},{"code":401,"indent":1,"parameters":["\\C[8] Yuma: \\C[0]Ah é, \\.sonho lúcido."]},{"code":235,"indent":1,"parameters":[2]},{"code":230,"indent":1,"parameters":[20]},{"code":231,"indent":1,"parameters":[2,"Badyuma5",0,0,330,125,80,80,255,0]},{"code":101,"indent":1,"parameters":["",0,1,2]},{"code":401,"indent":1,"parameters":["\\C[8] Yuma: \\C[0]Já já eu acordo e tá tudo resolvido."]},{"code":235,"indent":1,"parameters":[2]},{"code":230,"indent":1,"parameters":[60]},{"code":356,"indent":1,"parameters":["MSGSE TALK 3"]},{"code":231,"indent":1,"parameters":[3,"Coelhosis",0,0,430,215,65,65,255,0]},{"code":101,"indent":1,"parameters":["",0,1,2]},{"code":401,"indent":1,"parameters":["\\C[6] Marisol: \\C[0]Você pensa que é um sonho?"]},{"code":235,"indent":1,"parameters":[3]},{"code":230,"indent":1,"parameters":[50]},{"code":231,"indent":1,"parameters":[3,"Coelhosis",0,0,430,215,65,65,255,0]},{"code":101,"indent":1,"parameters":["",0,1,2]},{"code":401,"indent":1,"parameters":["\\C[6] Marisol: \\C[0]Tadinha..."]},{"code":235,"indent":1,"parameters":[3]},{"code":230,"indent":1,"parameters":[30]},{"code":231,"indent":1,"parameters":[3,"Coelhosis",0,0,430,215,65,65,255,0]},{"code":101,"indent":1,"parameters":["",0,1,2]},{"code":401,"indent":1,"parameters":["\\C[6] Marisol: \\C[0]Queria eu que fosse."]},{"code":235,"indent":1,"parameters":[3]},{"code":230,"indent":1,"parameters":[40]},{"code":231,"indent":1,"parameters":[3,"Coelhosis",0,0,430,215,65,65,255,0]},{"code":101,"indent":1,"parameters":["",0,1,2]},{"code":401,"indent":1,"parameters":["\\C[6] Marisol: \\C[0]Mas o buraco é bem mais embaixo..."]},{"code":235,"indent":1,"parameters":[3]},{"code":230,"indent":1,"parameters":[65]},{"code":231,"indent":1,"parameters":[3,"Coelhosis",0,0,430,215,65,65,255,0]},{"code":101,"indent":1,"parameters":["",0,1,2]},{"code":401,"indent":1,"parameters":["\\C[6] Marisol: \\C[0]A gente pode discutir os detalhes depois,"]},{"code":230,"indent":1,"parameters":[20]},{"code":101,"indent":1,"parameters":["",0,1,2]},{"code":401,"indent":1,"parameters":["\\C[6] Marisol: \\C[0]Você precisa vir comigo."]},{"code":235,"indent":1,"parameters":[3]},{"code":230,"indent":1,"parameters":[30]},{"code":231,"indent":1,"parameters":[3,"Coelhosis",0,0,430,215,65,65,255,0]},{"code":101,"indent":1,"parameters":["",0,1,2]},{"code":401,"indent":1,"parameters":["\\C[6] Marisol: \\C[0]Ah menos que queria esperar até a dona aranha voltar."]},{"code":235,"indent":1,"parameters":[3]},{"code":230,"indent":1,"parameters":[30]},{"code":356,"indent":1,"parameters":["MSGSE TALK DEFAULT"]},{"code":231,"indent":1,"parameters":[2,"Badyuma5",0,0,330,125,80,80,255,0]},{"code":101,"indent":1,"parameters":["",0,1,2]},{"code":401,"indent":1,"parameters":["\\C[8] Yuma: \\C[0]..."]},{"code":235,"indent":1,"parameters":[2]},{"code":230,"indent":1,"parameters":[40]},{"code":356,"indent":1,"parameters":["MSGSE TALK 3"]},{"code":231,"indent":1,"parameters":[3,"Coelhosis",0,0,430,215,65,65,255,0]},{"code":101,"indent":1,"parameters":["",0,1,2]},{"code":401,"indent":1,"parameters":["\\C[6] Marisol: \\C[0]Mas você quem sabe né, \\.o sonho é seu."]},{"code":235,"indent":1,"parameters":[3]},{"code":230,"indent":1,"parameters":[60]},{"code":231,"indent":1,"parameters":[1,"Coelhosis",0,0,430,215,65,65,255,0]},{"code":101,"indent":1,"parameters":["",0,1,2]},{"code":401,"indent":1,"parameters":["\\C[6] Marisol: \\C[0]Se mudar de idéia,"]},{"code":101,"indent":1,"parameters":["",0,1,2]},{"code":401,"indent":1,"parameters":["\\C[6] Marisol: \\C[0]A porta tá bem ali."]},{"code":235,"indent":1,"parameters":[1]},{"code":205,"indent":1,"parameters":[-1,{"list":[{"code":41,"parameters":["$Yuma",0],"indent":null},{"code":0}],"repeat":false,"skippable":false,"wait":false}]},{"code":505,"indent":1,"parameters":[{"code":41,"parameters":["$Yuma",0],"indent":null}]},{"code":242,"indent":1,"parameters":[1]},{"code":201,"indent":1,"parameters":[0,127,3,9,8,0]},{"code":205,"indent":1,"parameters":[-1,{"list":[{"code":41,"parameters":["$Yuma",0],"indent":null},{"code":0}],"repeat":false,"skippable":false,"wait":false}]},{"code":505,"indent":1,"parameters":[{"code":41,"parameters":["$Yuma",0],"indent":null}]},{"code":205,"indent":1,"parameters":[2,{"list":[{"code":19,"indent":null},{"code":4,"indent":null},{"code":4,"indent":null},{"code":4,"indent":null},{"code":4,"indent":null},{"code":0}],"repeat":false,"skippable":false,"wait":true}]},{"code":505,"indent":1,"parameters":[{"code":19,"indent":null}]},{"code":505,"indent":1,"parameters":[{"code":4,"indent":null}]},{"code":505,"indent":1,"parameters":[{"code":4,"indent":null}]},{"code":505,"indent":1,"parameters":[{"code":4,"indent":null}]},{"code":505,"indent":1,"parameters":[{"code":4,"indent":null}]},{"code":250,"indent":1,"parameters":[{"name":"tm2_chair003","volume":30,"pitch":100,"pan":0}]},{"code":121,"indent":1,"parameters":[40,40,0]},{"code":221,"indent":1,"parameters":[]},{"code":201,"indent":1,"parameters":[0,127,3,5,8,0]},{"code":356,"indent":1,"parameters":["mv3d camera target ＠player 0"]},{"code":356,"indent":1,"parameters":["show_all_indicators"]},{"code":356,"indent":1,"parameters":["mv3d dist 5 0"]},{"code":222,"indent":1,"parameters":[]},{"code":230,"indent":1,"parameters":[30]},{"code":203,"indent":1,"parameters":[2,0,6,19,0]},{"code":250,"indent":1,"parameters":[{"name":"Close1","volume":20,"pitch":100,"pan":0}]},{"code":230,"indent":1,"parameters":[90]},{"code":356,"indent":1,"parameters":["MSGSE TALK DEFAULT"]},{"code":231,"indent":1,"parameters":[2,"Badyuma5",0,0,330,125,80,80,255,0]},{"code":101,"indent":1,"parameters":["",0,1,2]},{"code":401,"indent":1,"parameters":["\\C[8] Yuma: \\C[0]..."]},{"code":235,"indent":1,"parameters":[2]},{"code":230,"indent":1,"parameters":[30]},{"code":231,"indent":1,"parameters":[2,"Badyuma5",0,0,330,125,80,80,255,0]},{"code":101,"indent":1,"parameters":["",0,1,2]},{"code":401,"indent":1,"parameters":["\\C[8] Yuma: \\C[0]Isso não faz sentido..."]},{"code":235,"indent":1,"parameters":[2]},{"code":230,"indent":1,"parameters":[70]},{"code":231,"indent":1,"parameters":[2,"Badyuma5",0,0,330,125,80,80,255,0]},{"code":101,"indent":1,"parameters":["",0,1,2]},{"code":401,"indent":1,"parameters":["\\C[8] Yuma: \\C[0]Calma Yuma..."]},{"code":235,"indent":1,"parameters":[2]},{"code":230,"indent":1,"parameters":[20]},{"code":231,"indent":1,"parameters":[2,"Badyuma5",0,0,330,125,80,80,255,0]},{"code":101,"indent":1,"parameters":["",0,1,2]},{"code":401,"indent":1,"parameters":["\\C[8] Yuma: \\C[0]Você vai acordar a qualquer instante."]},{"code":101,"indent":1,"parameters":["",0,1,2]},{"code":401,"indent":1,"parameters":["\\C[8] Yuma: \\C[0]Só ta demorando um pouco mais que o normal..."]},{"code":235,"indent":1,"parameters":[2]},{"code":0,"indent":1,"parameters":[]},{"code":412,"indent":0,"parameters":[]},{"code":0,"indent":0,"parameters":[]}],"moveFrequency":3,"moveRoute":{"list":[{"code":0,"parameters":[]}],"repeat":true,"skippable":false,"wait":false},"moveSpeed":3,"moveType":0,"priorityType":0,"stepAnime":false,"through":false,"trigger":1,"walkAnime":true}],"x":3,"y":9},
{"id":9,"name":"EV009","note":"","pages":[{"conditions":{"actorId":1,"actorValid":false,"itemId":1,"itemValid":false,"selfSwitchCh":"A","selfSwitchValid":false,"switch1Id":1,"switch1Valid":false,"switch2Id":1,"switch2Valid":false,"variableId":1,"variableValid":false,"variableValue":0},"directionFix":false,"image":{"tileId":0,"characterName":"","direction":2,"pattern":2,"characterIndex":0},"list":[{"code":0,"indent":0,"parameters":[]}],"moveFrequency":3,"moveRoute":{"list":[{"code":0,"parameters":[]}],"repeat":true,"skippable":false,"wait":false},"moveSpeed":3,"moveType":0,"priorityType":1,"stepAnime":false,"through":false,"trigger":0,"walkAnime":true}],"x":4,"y":17},
{"id":10,"name":"EV010","note":"","pages":[{"conditions":{"actorId":1,"actorValid":false,"itemId":1,"itemValid":false,"selfSwitchCh":"A","selfSwitchValid":false,"switch1Id":31,"switch1Valid":false,"switch2Id":1,"switch2Valid":false,"variableId":1,"variableValid":false,"variableValue":0},"directionFix":false,"image":{"characterIndex":0,"characterName":"","direction":2,"pattern":0,"tileId":0},"list":[{"code":111,"indent":0,"parameters":[6,-1,8]},{"code":221,"indent":1,"parameters":[]},{"code":201,"indent":1,"parameters":[0,127,3,9,8,2]},{"code":121,"indent":1,"parameters":[297,297,0]},{"code":356,"indent":1,"parameters":["mv3d camera target ＠e2 0"]},{"code":356,"indent":1,"parameters":["mv3d dist 5 0"]},{"code":222,"indent":1,"parameters":[]},{"code":250,"indent":1,"parameters":[{"name":"Rabbit","volume":40,"pitch":90,"pan":-40}]},{"code":356,"indent":1,"parameters":["MSGSE TALK 3"]},{"code":231,"indent":1,"parameters":[1,"Coelhosis",0,0,430,215,65,65,255,0]},{"code":101,"indent":1,"parameters":["",0,1,2]},{"code":401,"indent":1,"parameters":["\\C[6] ???: \\C[0]Booo!"]},{"code":235,"indent":1,"parameters":[1]},{"code":356,"indent":1,"parameters":["MSGSE TALK DEFAULT"]},{"code":356,"indent":1,"parameters":["mv3d camera target ＠player 0"]},{"code":356,"indent":1,"parameters":["mv3d dist 6 0"]},{"code":205,"indent":1,"parameters":[-1,{"list":[{"code":14,"parameters":[0,0],"indent":null},{"code":0}],"repeat":false,"skippable":false,"wait":false}]},{"code":505,"indent":1,"parameters":[{"code":14,"parameters":[0,0],"indent":null}]},{"code":231,"indent":1,"parameters":[2,"Badyuma4",0,0,330,125,80,80,255,0]},{"code":101,"indent":1,"parameters":["",0,1,2]},{"code":401,"indent":1,"parameters":["\\C[8] Yuma: \\C[0]Aaaah!"]},{"code":101,"indent":1,"parameters":["",0,1,2]},{"code":401,"indent":1,"parameters":["\\C[8] Yuma: \\C[0]Mas que merda é essa..."]},{"code":235,"indent":1,"parameters":[2]},{"code":230,"indent":1,"parameters":[40]},{"code":356,"indent":1,"parameters":["hide_all_indicators"]},{"code":201,"indent":1,"parameters":[0,127,3,10,8,2]},{"code":356,"indent":1,"parameters":["mv3d yaw 0 0"]},{"code":356,"indent":1,"parameters":["mv3d camera target ＠e2 0"]},{"code":356,"indent":1,"parameters":["mv3d dist 4 0"]},{"code":356,"indent":1,"parameters":["mv3d height 0.7 0"]},{"code":241,"indent":1,"parameters":[{"name":"musicairma","volume":10,"pitch":70,"pan":0}]},{"code":356,"indent":1,"parameters":["MSGSE TALK 3"]},{"code":231,"indent":1,"parameters":[1,"Coelhosis",0,0,430,215,65,65,255,0]},{"code":101,"indent":1,"parameters":["",0,1,2]},{"code":401,"indent":1,"parameters":["\\C[6] ???: \\C[0]Assustei você?"]},{"code":235,"indent":1,"parameters":[1]},{"code":230,"indent":1,"parameters":[20]},{"code":231,"indent":1,"parameters":[1,"Coelhosis",0,0,430,215,65,65,255,0]},{"code":101,"indent":1,"parameters":["",0,1,2]},{"code":401,"indent":1,"parameters":["\\C[6] ???: \\C[0]Hahah."]},{"code":235,"indent":1,"parameters":[1]},{"code":230,"indent":1,"parameters":[20]},{"code":231,"indent":1,"parameters":[1,"Coelhosis",0,0,430,215,65,65,255,0]},{"code":101,"indent":1,"parameters":["",0,1,2]},{"code":401,"indent":1,"parameters":["\\C[6] ???: \\C[0]Que bom, \\.essa era a intenção."]},{"code":356,"indent":1,"parameters":["MSGSE TALK DEFAULT"]},{"code":235,"indent":1,"parameters":[1]},{"code":230,"indent":1,"parameters":[50]},{"code":231,"indent":1,"parameters":[2,"Badyuma2",0,0,330,125,80,80,255,0]},{"code":101,"indent":1,"parameters":["",0,1,2]},{"code":401,"indent":1,"parameters":["\\C[8] Yuma: \\C[0]..."]},{"code":235,"indent":1,"parameters":[2]},{"code":230,"indent":1,"parameters":[40]},{"code":231,"indent":1,"parameters":[2,"Badyuma5",0,0,330,125,80,80,255,0]},{"code":101,"indent":1,"parameters":["",0,1,2]},{"code":401,"indent":1,"parameters":["\\C[8] Yuma: \\C[0]Quem... \\.\\.é você...?"]},{"code":235,"indent":1,"parameters":[2]},{"code":230,"indent":1,"parameters":[50]},{"code":356,"indent":1,"parameters":["MSGSE TALK 3"]},{"code":231,"indent":1,"parameters":[3,"Coelhosis",0,0,430,215,65,65,255,0]},{"code":101,"indent":1,"parameters":["",0,1,2]},{"code":401,"indent":1,"parameters":["\\C[6] ???: \\C[0]Ah, \\.desculpe,"]},{"code":101,"indent":1,"parameters":["",0,1,2]},{"code":401,"indent":1,"parameters":["\\C[6] ???: \\C[0]Que falta de educação a minha."]},{"code":235,"indent":1,"parameters":[3]},{"code":230,"indent":1,"parameters":[30]},{"code":231,"indent":1,"parameters":[3,"Coelhosis",0,0,430,215,65,65,255,0]},{"code":101,"indent":1,"parameters":["",0,1,2]},{"code":401,"indent":1,"parameters":["\\C[6] Marisol: \\C[0]Eu me chamo Marisol."]},{"code":235,"indent":1,"parameters":[3]},{"code":230,"indent":1,"parameters":[20]},{"code":231,"indent":1,"parameters":[3,"Coelhosis",0,0,430,215,65,65,255,0]},{"code":101,"indent":1,"parameters":["",0,1,2]},{"code":401,"indent":1,"parameters":["\\C[6] Marisol: \\C[0]Mas pode me chamar de Mari."]},{"code":235,"indent":1,"parameters":[3]},{"code":230,"indent":1,"parameters":[40]},{"code":231,"indent":1,"parameters":[3,"Coelhosis",0,0,430,215,65,65,255,0]},{"code":101,"indent":1,"parameters":["",0,1,2]},{"code":401,"indent":1,"parameters":["\\C[6] Marisol: \\C[0]Lembre desse nome,"]},{"code":101,"indent":1,"parameters":["",0,1,2]},{"code":401,"indent":1,"parameters":["\\C[6] Marisol: \\C[0]Porque é o nome da sua salvadora!"]},{"code":235,"indent":1,"parameters":[3]},{"code":230,"indent":1,"parameters":[60]},{"code":356,"indent":1,"parameters":["MSGSE TALK DEFAULT"]},{"code":231,"indent":1,"parameters":[2,"Badyuma5",0,0,330,125,80,80,255,0]},{"code":101,"indent":1,"parameters":["",0,1,2]},{"code":401,"indent":1,"parameters":["\\C[8] Yuma: \\C[0]Quê...?"]},{"code":235,"indent":1,"parameters":[2]},{"code":230,"indent":1,"parameters":[30]},{"code":231,"indent":1,"parameters":[3,"Coelhosis",0,0,430,215,65,65,255,0]},{"code":101,"indent":1,"parameters":["",0,1,2]},{"code":401,"indent":1,"parameters":["\\C[6] Marisol: \\C[0]Isso mesmo que ouviu,"]},{"code":101,"indent":1,"parameters":["",0,1,2]},{"code":401,"indent":1,"parameters":["\\C[6] Marisol: \\C[0]Eu vim te tirar desse lugar."]},{"code":235,"indent":1,"parameters":[3]},{"code":230,"indent":1,"parameters":[40]},{"code":356,"indent":1,"parameters":["MSGSE TALK 3"]},{"code":231,"indent":1,"parameters":[3,"Coelhosis",0,0,430,215,65,65,255,0]},{"code":101,"indent":1,"parameters":["",0,1,2]},{"code":401,"indent":1,"parameters":["\\C[6] Marisol: \\C[0]Tinha te visto correndo desesperada mais cedo."]},{"code":235,"indent":1,"parameters":[3]},{"code":230,"indent":1,"parameters":[25]},{"code":231,"indent":1,"parameters":[3,"Coelhosis",0,0,430,215,65,65,255,0]},{"code":101,"indent":1,"parameters":["",0,1,2]},{"code":401,"indent":1,"parameters":["\\C[6] Marisol: \\C[0]Que bom que ainda está viva."]},{"code":235,"indent":1,"parameters":[3]},{"code":230,"indent":1,"parameters":[60]},{"code":231,"indent":1,"parameters":[3,"Coelhosis",0,0,430,215,65,65,255,0]},{"code":101,"indent":1,"parameters":["",0,1,2]},{"code":401,"indent":1,"parameters":["\\C[6] Marisol: \\C[0]Eu até enfrentaria aquele bicho,"]},{"code":101,"indent":1,"parameters":["",0,1,2]},{"code":401,"indent":1,"parameters":["\\C[6] Marisol: \\C[0]Mas sabe como é... \\.heh"]},{"code":235,"indent":1,"parameters":[3]},{"code":230,"indent":1,"parameters":[30]},{"code":231,"indent":1,"parameters":[3,"Coelhosis",0,0,430,215,65,65,255,0]},{"code":101,"indent":1,"parameters":["",0,1,2]},{"code":401,"indent":1,"parameters":["\\C[6] Marisol: \\C[0]Odeio aranhas..."]},{"code":235,"indent":1,"parameters":[3]},{"code":230,"indent":1,"parameters":[40]},{"code":356,"indent":1,"parameters":["MSGSE TALK DEFAULT"]},{"code":231,"indent":1,"parameters":[2,"Badyuma5",0,0,330,125,80,80,255,0]},{"code":101,"indent":1,"parameters":["",0,1,2]},{"code":401,"indent":1,"parameters":["\\C[8] Yuma: \\C[0]Do que está falando...?"]},{"code":101,"indent":1,"parameters":["",0,1,2]},{"code":401,"indent":1,"parameters":["\\C[8] Yuma: \\C[0]Eu não te conheço."]},{"code":235,"indent":1,"parameters":[2]},{"code":230,"indent":1,"parameters":[60]},{"code":231,"indent":1,"parameters":[2,"Badyuma5",0,0,330,125,80,80,255,0]},{"code":101,"indent":1,"parameters":["",0,1,2]},{"code":401,"indent":1,"parameters":["\\C[8] Yuma: \\C[0]..."]},{"code":235,"indent":1,"parameters":[2]},{"code":230,"indent":1,"parameters":[30]},{"code":231,"indent":1,"parameters":[2,"Badyuma5",0,0,330,125,80,80,255,0]},{"code":101,"indent":1,"parameters":["",0,1,2]},{"code":401,"indent":1,"parameters":["\\C[8] Yuma: \\C[0]Nem sei porque estou tendo essa conversa..."]},{"code":101,"indent":1,"parameters":["",0,1,2]},{"code":401,"indent":1,"parameters":["\\C[8] Yuma: \\C[0]Você não é real."]},{"code":235,"indent":1,"parameters":[2]},{"code":230,"indent":1,"parameters":[30]},{"code":356,"indent":1,"parameters":["MSGSE TALK 3"]},{"code":231,"indent":1,"parameters":[3,"Coelhosis",0,0,430,215,65,65,255,0]},{"code":101,"indent":1,"parameters":["",0,1,2]},{"code":401,"indent":1,"parameters":["\\C[6] Marisol: \\C[0]Pera, \\.como é?"]},{"code":101,"indent":1,"parameters":["",0,1,2]},{"code":401,"indent":1,"parameters":["\\C[6] Marisol: \\C[0]Eu não sou real? \\.hahah"]},{"code":235,"indent":1,"parameters":[3]},{"code":230,"indent":1,"parameters":[20]},{"code":231,"indent":1,"parameters":[3,"Coelhosis",0,0,430,215,65,65,255,0]},{"code":101,"indent":1,"parameters":["",0,1,2]},{"code":401,"indent":1,"parameters":["\\C[6] Marisol: \\C[0]Aquela mãezona aranha te acertou na cabeça, \\.foi?"]},{"code":235,"indent":1,"parameters":[3]},{"code":230,"indent":1,"parameters":[30]},{"code":356,"indent":1,"parameters":["MSGSE TALK DEFAULT"]},{"code":231,"indent":1,"parameters":[2,"Badyuma5",0,0,330,125,80,80,255,0]},{"code":101,"indent":1,"parameters":["",0,1,2]},{"code":401,"indent":1,"parameters":["\\C[8] Yuma: \\C[0]Esse é um daqueles sonhos que você parece acordado."]},{"code":235,"indent":1,"parameters":[2]},{"code":230,"indent":1,"parameters":[20]},{"code":231,"indent":1,"parameters":[2,"Badyuma5",0,0,330,125,80,80,255,0]},{"code":101,"indent":1,"parameters":["",0,1,2]},{"code":401,"indent":1,"parameters":["\\C[8] Yuma: \\C[0]Não lembro o nome..."]},{"code":235,"indent":1,"parameters":[2]},{"code":230,"indent":1,"parameters":[30]},{"code":231,"indent":1,"parameters":[2,"Badyuma5",0,0,330,125,80,80,255,0]},{"code":101,"indent":1,"parameters":["",0,1,2]},{"code":401,"indent":1,"parameters":["\\C[8] Yuma: \\C[0]Ah é, \\.sonho lúcido."]},{"code":235,"indent":1,"parameters":[2]},{"code":230,"indent":1,"parameters":[20]},{"code":231,"indent":1,"parameters":[2,"Badyuma5",0,0,330,125,80,80,255,0]},{"code":101,"indent":1,"parameters":["",0,1,2]},{"code":401,"indent":1,"parameters":["\\C[8] Yuma: \\C[0]Já já eu acordo e tá tudo resolvido."]},{"code":235,"indent":1,"parameters":[2]},{"code":230,"indent":1,"parameters":[60]},{"code":356,"indent":1,"parameters":["MSGSE TALK 3"]},{"code":231,"indent":1,"parameters":[3,"Coelhosis",0,0,430,215,65,65,255,0]},{"code":101,"indent":1,"parameters":["",0,1,2]},{"code":401,"indent":1,"parameters":["\\C[6] Marisol: \\C[0]Você pensa que é um sonho?"]},{"code":235,"indent":1,"parameters":[3]},{"code":230,"indent":1,"parameters":[50]},{"code":231,"indent":1,"parameters":[3,"Coelhosis",0,0,430,215,65,65,255,0]},{"code":101,"indent":1,"parameters":["",0,1,2]},{"code":401,"indent":1,"parameters":["\\C[6] Marisol: \\C[0]Tadinha..."]},{"code":235,"indent":1,"parameters":[3]},{"code":230,"indent":1,"parameters":[30]},{"code":231,"indent":1,"parameters":[3,"Coelhosis",0,0,430,215,65,65,255,0]},{"code":101,"indent":1,"parameters":["",0,1,2]},{"code":401,"indent":1,"parameters":["\\C[6] Marisol: \\C[0]Queria eu que fosse."]},{"code":235,"indent":1,"parameters":[3]},{"code":230,"indent":1,"parameters":[40]},{"code":231,"indent":1,"parameters":[3,"Coelhosis",0,0,430,215,65,65,255,0]},{"code":101,"indent":1,"parameters":["",0,1,2]},{"code":401,"indent":1,"parameters":["\\C[6] Marisol: \\C[0]Mas o buraco é bem mais embaixo..."]},{"code":235,"indent":1,"parameters":[3]},{"code":230,"indent":1,"parameters":[65]},{"code":231,"indent":1,"parameters":[3,"Coelhosis",0,0,430,215,65,65,255,0]},{"code":101,"indent":1,"parameters":["",0,1,2]},{"code":401,"indent":1,"parameters":["\\C[6] Marisol: \\C[0]A gente pode discutir os detalhes depois,"]},{"code":230,"indent":1,"parameters":[20]},{"code":101,"indent":1,"parameters":["",0,1,2]},{"code":401,"indent":1,"parameters":["\\C[6] Marisol: \\C[0]Você precisa vir comigo."]},{"code":235,"indent":1,"parameters":[3]},{"code":230,"indent":1,"parameters":[30]},{"code":231,"indent":1,"parameters":[3,"Coelhosis",0,0,430,215,65,65,255,0]},{"code":101,"indent":1,"parameters":["",0,1,2]},{"code":401,"indent":1,"parameters":["\\C[6] Marisol: \\C[0]Ah menos que queria esperar até a dona aranha voltar."]},{"code":235,"indent":1,"parameters":[3]},{"code":230,"indent":1,"parameters":[30]},{"code":356,"indent":1,"parameters":["MSGSE TALK DEFAULT"]},{"code":231,"indent":1,"parameters":[2,"Badyuma5",0,0,330,125,80,80,255,0]},{"code":101,"indent":1,"parameters":["",0,1,2]},{"code":401,"indent":1,"parameters":["\\C[8] Yuma: \\C[0]..."]},{"code":235,"indent":1,"parameters":[2]},{"code":230,"indent":1,"parameters":[40]},{"code":356,"indent":1,"parameters":["MSGSE TALK 3"]},{"code":231,"indent":1,"parameters":[3,"Coelhosis",0,0,430,215,65,65,255,0]},{"code":101,"indent":1,"parameters":["",0,1,2]},{"code":401,"indent":1,"parameters":["\\C[6] Marisol: \\C[0]Mas você quem sabe né, \\.o sonho é seu."]},{"code":235,"indent":1,"parameters":[3]},{"code":230,"indent":1,"parameters":[60]},{"code":231,"indent":1,"parameters":[1,"Coelhosis",0,0,430,215,65,65,255,0]},{"code":101,"indent":1,"parameters":["",0,1,2]},{"code":401,"indent":1,"parameters":["\\C[6] Marisol: \\C[0]Se mudar de idéia,"]},{"code":101,"indent":1,"parameters":["",0,1,2]},{"code":401,"indent":1,"parameters":["\\C[6] Marisol: \\C[0]A porta tá bem ali."]},{"code":235,"indent":1,"parameters":[1]},{"code":205,"indent":1,"parameters":[-1,{"list":[{"code":41,"parameters":["$Yuma",0],"indent":null},{"code":0}],"repeat":false,"skippable":false,"wait":false}]},{"code":505,"indent":1,"parameters":[{"code":41,"parameters":["$Yuma",0],"indent":null}]},{"code":242,"indent":1,"parameters":[1]},{"code":201,"indent":1,"parameters":[0,127,3,9,8,0]},{"code":205,"indent":1,"parameters":[-1,{"list":[{"code":41,"parameters":["$Yuma",0],"indent":null},{"code":0}],"repeat":false,"skippable":false,"wait":false}]},{"code":505,"indent":1,"parameters":[{"code":41,"parameters":["$Yuma",0],"indent":null}]},{"code":205,"indent":1,"parameters":[2,{"list":[{"code":19,"indent":null},{"code":4,"indent":null},{"code":4,"indent":null},{"code":4,"indent":null},{"code":4,"indent":null},{"code":0}],"repeat":false,"skippable":false,"wait":true}]},{"code":505,"indent":1,"parameters":[{"code":19,"indent":null}]},{"code":505,"indent":1,"parameters":[{"code":4,"indent":null}]},{"code":505,"indent":1,"parameters":[{"code":4,"indent":null}]},{"code":505,"indent":1,"parameters":[{"code":4,"indent":null}]},{"code":505,"indent":1,"parameters":[{"code":4,"indent":null}]},{"code":250,"indent":1,"parameters":[{"name":"tm2_chair003","volume":30,"pitch":100,"pan":0}]},{"code":121,"indent":1,"parameters":[40,40,0]},{"code":221,"indent":1,"parameters":[]},{"code":201,"indent":1,"parameters":[0,127,3,5,8,0]},{"code":356,"indent":1,"parameters":["mv3d camera target ＠player 0"]},{"code":356,"indent":1,"parameters":["show_all_indicators"]},{"code":356,"indent":1,"parameters":["mv3d dist 5 0"]},{"code":222,"indent":1,"parameters":[]},{"code":230,"indent":1,"parameters":[30]},{"code":203,"indent":1,"parameters":[2,0,6,19,0]},{"code":250,"indent":1,"parameters":[{"name":"Close1","volume":20,"pitch":100,"pan":0}]},{"code":230,"indent":1,"parameters":[90]},{"code":356,"indent":1,"parameters":["MSGSE TALK DEFAULT"]},{"code":231,"indent":1,"parameters":[2,"Badyuma5",0,0,330,125,80,80,255,0]},{"code":101,"indent":1,"parameters":["",0,1,2]},{"code":401,"indent":1,"parameters":["\\C[8] Yuma: \\C[0]..."]},{"code":235,"indent":1,"parameters":[2]},{"code":230,"indent":1,"parameters":[30]},{"code":231,"indent":1,"parameters":[2,"Badyuma5",0,0,330,125,80,80,255,0]},{"code":101,"indent":1,"parameters":["",0,1,2]},{"code":401,"indent":1,"parameters":["\\C[8] Yuma: \\C[0]Isso não faz sentido..."]},{"code":235,"indent":1,"parameters":[2]},{"code":230,"indent":1,"parameters":[70]},{"code":231,"indent":1,"parameters":[2,"Badyuma5",0,0,330,125,80,80,255,0]},{"code":101,"indent":1,"parameters":["",0,1,2]},{"code":401,"indent":1,"parameters":["\\C[8] Yuma: \\C[0]Calma Yuma..."]},{"code":235,"indent":1,"parameters":[2]},{"code":230,"indent":1,"parameters":[20]},{"code":231,"indent":1,"parameters":[2,"Badyuma5",0,0,330,125,80,80,255,0]},{"code":101,"indent":1,"parameters":["",0,1,2]},{"code":401,"indent":1,"parameters":["\\C[8] Yuma: \\C[0]Você vai acordar a qualquer instante."]},{"code":101,"indent":1,"parameters":["",0,1,2]},{"code":401,"indent":1,"parameters":["\\C[8] Yuma: \\C[0]Só ta demorando um pouco mais que o normal..."]},{"code":235,"indent":1,"parameters":[2]},{"code":0,"indent":1,"parameters":[]},{"code":412,"indent":0,"parameters":[]},{"code":0,"indent":0,"parameters":[]}],"moveFrequency":3,"moveRoute":{"list":[{"code":0,"parameters":[]}],"repeat":true,"skippable":false,"wait":false},"moveSpeed":3,"moveType":0,"priorityType":0,"stepAnime":false,"through":false,"trigger":1,"walkAnime":true}],"x":2,"y":9},
{"id":11,"name":"EV011","note":"","pages":[{"conditions":{"actorId":1,"actorValid":false,"itemId":1,"itemValid":false,"selfSwitchCh":"A","selfSwitchValid":false,"switch1Id":31,"switch1Valid":false,"switch2Id":1,"switch2Valid":false,"variableId":1,"variableValid":false,"variableValue":0},"directionFix":false,"image":{"characterIndex":0,"characterName":"","direction":2,"pattern":0,"tileId":0},"list":[{"code":111,"indent":0,"parameters":[6,-1,8]},{"code":221,"indent":1,"parameters":[]},{"code":201,"indent":1,"parameters":[0,127,3,9,8,2]},{"code":121,"indent":1,"parameters":[297,297,0]},{"code":356,"indent":1,"parameters":["mv3d camera target ＠e2 0"]},{"code":356,"indent":1,"parameters":["mv3d dist 5 0"]},{"code":222,"indent":1,"parameters":[]},{"code":250,"indent":1,"parameters":[{"name":"Rabbit","volume":40,"pitch":90,"pan":-40}]},{"code":356,"indent":1,"parameters":["MSGSE TALK 3"]},{"code":231,"indent":1,"parameters":[1,"Coelhosis",0,0,430,215,65,65,255,0]},{"code":101,"indent":1,"parameters":["",0,1,2]},{"code":401,"indent":1,"parameters":["\\C[6] ???: \\C[0]Booo!"]},{"code":235,"indent":1,"parameters":[1]},{"code":356,"indent":1,"parameters":["MSGSE TALK DEFAULT"]},{"code":356,"indent":1,"parameters":["mv3d camera target ＠player 0"]},{"code":356,"indent":1,"parameters":["mv3d dist 6 0"]},{"code":205,"indent":1,"parameters":[-1,{"list":[{"code":14,"parameters":[0,0],"indent":null},{"code":0}],"repeat":false,"skippable":false,"wait":false}]},{"code":505,"indent":1,"parameters":[{"code":14,"parameters":[0,0],"indent":null}]},{"code":231,"indent":1,"parameters":[2,"Badyuma4",0,0,330,125,80,80,255,0]},{"code":101,"indent":1,"parameters":["",0,1,2]},{"code":401,"indent":1,"parameters":["\\C[8] Yuma: \\C[0]Aaaah!"]},{"code":101,"indent":1,"parameters":["",0,1,2]},{"code":401,"indent":1,"parameters":["\\C[8] Yuma: \\C[0]Mas que merda é essa..."]},{"code":235,"indent":1,"parameters":[2]},{"code":230,"indent":1,"parameters":[40]},{"code":356,"indent":1,"parameters":["hide_all_indicators"]},{"code":201,"indent":1,"parameters":[0,127,3,10,8,2]},{"code":356,"indent":1,"parameters":["mv3d yaw 0 0"]},{"code":356,"indent":1,"parameters":["mv3d camera target ＠e2 0"]},{"code":356,"indent":1,"parameters":["mv3d dist 4 0"]},{"code":356,"indent":1,"parameters":["mv3d height 0.7 0"]},{"code":241,"indent":1,"parameters":[{"name":"musicairma","volume":10,"pitch":70,"pan":0}]},{"code":356,"indent":1,"parameters":["MSGSE TALK 3"]},{"code":231,"indent":1,"parameters":[1,"Coelhosis",0,0,430,215,65,65,255,0]},{"code":101,"indent":1,"parameters":["",0,1,2]},{"code":401,"indent":1,"parameters":["\\C[6] ???: \\C[0]Assustei você?"]},{"code":235,"indent":1,"parameters":[1]},{"code":230,"indent":1,"parameters":[20]},{"code":231,"indent":1,"parameters":[1,"Coelhosis",0,0,430,215,65,65,255,0]},{"code":101,"indent":1,"parameters":["",0,1,2]},{"code":401,"indent":1,"parameters":["\\C[6] ???: \\C[0]Hahah."]},{"code":235,"indent":1,"parameters":[1]},{"code":230,"indent":1,"parameters":[20]},{"code":231,"indent":1,"parameters":[1,"Coelhosis",0,0,430,215,65,65,255,0]},{"code":101,"indent":1,"parameters":["",0,1,2]},{"code":401,"indent":1,"parameters":["\\C[6] ???: \\C[0]Que bom, \\.essa era a intenção."]},{"code":356,"indent":1,"parameters":["MSGSE TALK DEFAULT"]},{"code":235,"indent":1,"parameters":[1]},{"code":230,"indent":1,"parameters":[50]},{"code":231,"indent":1,"parameters":[2,"Badyuma2",0,0,330,125,80,80,255,0]},{"code":101,"indent":1,"parameters":["",0,1,2]},{"code":401,"indent":1,"parameters":["\\C[8] Yuma: \\C[0]..."]},{"code":235,"indent":1,"parameters":[2]},{"code":230,"indent":1,"parameters":[40]},{"code":231,"indent":1,"parameters":[2,"Badyuma5",0,0,330,125,80,80,255,0]},{"code":101,"indent":1,"parameters":["",0,1,2]},{"code":401,"indent":1,"parameters":["\\C[8] Yuma: \\C[0]Quem... \\.\\.é você...?"]},{"code":235,"indent":1,"parameters":[2]},{"code":230,"indent":1,"parameters":[50]},{"code":356,"indent":1,"parameters":["MSGSE TALK 3"]},{"code":231,"indent":1,"parameters":[3,"Coelhosis",0,0,430,215,65,65,255,0]},{"code":101,"indent":1,"parameters":["",0,1,2]},{"code":401,"indent":1,"parameters":["\\C[6] ???: \\C[0]Ah, \\.desculpe,"]},{"code":101,"indent":1,"parameters":["",0,1,2]},{"code":401,"indent":1,"parameters":["\\C[6] ???: \\C[0]Que falta de educação a minha."]},{"code":235,"indent":1,"parameters":[3]},{"code":230,"indent":1,"parameters":[30]},{"code":231,"indent":1,"parameters":[3,"Coelhosis",0,0,430,215,65,65,255,0]},{"code":101,"indent":1,"parameters":["",0,1,2]},{"code":401,"indent":1,"parameters":["\\C[6] Marisol: \\C[0]Eu me chamo Marisol."]},{"code":235,"indent":1,"parameters":[3]},{"code":230,"indent":1,"parameters":[20]},{"code":231,"indent":1,"parameters":[3,"Coelhosis",0,0,430,215,65,65,255,0]},{"code":101,"indent":1,"parameters":["",0,1,2]},{"code":401,"indent":1,"parameters":["\\C[6] Marisol: \\C[0]Mas pode me chamar de Mari."]},{"code":235,"indent":1,"parameters":[3]},{"code":230,"indent":1,"parameters":[40]},{"code":231,"indent":1,"parameters":[3,"Coelhosis",0,0,430,215,65,65,255,0]},{"code":101,"indent":1,"parameters":["",0,1,2]},{"code":401,"indent":1,"parameters":["\\C[6] Marisol: \\C[0]Lembre desse nome,"]},{"code":101,"indent":1,"parameters":["",0,1,2]},{"code":401,"indent":1,"parameters":["\\C[6] Marisol: \\C[0]Porque é o nome da sua salvadora!"]},{"code":235,"indent":1,"parameters":[3]},{"code":230,"indent":1,"parameters":[60]},{"code":356,"indent":1,"parameters":["MSGSE TALK DEFAULT"]},{"code":231,"indent":1,"parameters":[2,"Badyuma5",0,0,330,125,80,80,255,0]},{"code":101,"indent":1,"parameters":["",0,1,2]},{"code":401,"indent":1,"parameters":["\\C[8] Yuma: \\C[0]Quê...?"]},{"code":235,"indent":1,"parameters":[2]},{"code":230,"indent":1,"parameters":[30]},{"code":231,"indent":1,"parameters":[3,"Coelhosis",0,0,430,215,65,65,255,0]},{"code":101,"indent":1,"parameters":["",0,1,2]},{"code":401,"indent":1,"parameters":["\\C[6] Marisol: \\C[0]Isso mesmo que ouviu,"]},{"code":101,"indent":1,"parameters":["",0,1,2]},{"code":401,"indent":1,"parameters":["\\C[6] Marisol: \\C[0]Eu vim te tirar desse lugar."]},{"code":235,"indent":1,"parameters":[3]},{"code":230,"indent":1,"parameters":[40]},{"code":356,"indent":1,"parameters":["MSGSE TALK 3"]},{"code":231,"indent":1,"parameters":[3,"Coelhosis",0,0,430,215,65,65,255,0]},{"code":101,"indent":1,"parameters":["",0,1,2]},{"code":401,"indent":1,"parameters":["\\C[6] Marisol: \\C[0]Tinha te visto correndo desesperada mais cedo."]},{"code":235,"indent":1,"parameters":[3]},{"code":230,"indent":1,"parameters":[25]},{"code":231,"indent":1,"parameters":[3,"Coelhosis",0,0,430,215,65,65,255,0]},{"code":101,"indent":1,"parameters":["",0,1,2]},{"code":401,"indent":1,"parameters":["\\C[6] Marisol: \\C[0]Que bom que ainda está viva."]},{"code":235,"indent":1,"parameters":[3]},{"code":230,"indent":1,"parameters":[60]},{"code":231,"indent":1,"parameters":[3,"Coelhosis",0,0,430,215,65,65,255,0]},{"code":101,"indent":1,"parameters":["",0,1,2]},{"code":401,"indent":1,"parameters":["\\C[6] Marisol: \\C[0]Eu até enfrentaria aquele bicho,"]},{"code":101,"indent":1,"parameters":["",0,1,2]},{"code":401,"indent":1,"parameters":["\\C[6] Marisol: \\C[0]Mas sabe como é... \\.heh"]},{"code":235,"indent":1,"parameters":[3]},{"code":230,"indent":1,"parameters":[30]},{"code":231,"indent":1,"parameters":[3,"Coelhosis",0,0,430,215,65,65,255,0]},{"code":101,"indent":1,"parameters":["",0,1,2]},{"code":401,"indent":1,"parameters":["\\C[6] Marisol: \\C[0]Odeio aranhas..."]},{"code":235,"indent":1,"parameters":[3]},{"code":230,"indent":1,"parameters":[40]},{"code":356,"indent":1,"parameters":["MSGSE TALK DEFAULT"]},{"code":231,"indent":1,"parameters":[2,"Badyuma5",0,0,330,125,80,80,255,0]},{"code":101,"indent":1,"parameters":["",0,1,2]},{"code":401,"indent":1,"parameters":["\\C[8] Yuma: \\C[0]Do que está falando...?"]},{"code":101,"indent":1,"parameters":["",0,1,2]},{"code":401,"indent":1,"parameters":["\\C[8] Yuma: \\C[0]Eu não te conheço."]},{"code":235,"indent":1,"parameters":[2]},{"code":230,"indent":1,"parameters":[60]},{"code":231,"indent":1,"parameters":[2,"Badyuma5",0,0,330,125,80,80,255,0]},{"code":101,"indent":1,"parameters":["",0,1,2]},{"code":401,"indent":1,"parameters":["\\C[8] Yuma: \\C[0]..."]},{"code":235,"indent":1,"parameters":[2]},{"code":230,"indent":1,"parameters":[30]},{"code":231,"indent":1,"parameters":[2,"Badyuma5",0,0,330,125,80,80,255,0]},{"code":101,"indent":1,"parameters":["",0,1,2]},{"code":401,"indent":1,"parameters":["\\C[8] Yuma: \\C[0]Nem sei porque estou tendo essa conversa..."]},{"code":101,"indent":1,"parameters":["",0,1,2]},{"code":401,"indent":1,"parameters":["\\C[8] Yuma: \\C[0]Você não é real."]},{"code":235,"indent":1,"parameters":[2]},{"code":230,"indent":1,"parameters":[30]},{"code":356,"indent":1,"parameters":["MSGSE TALK 3"]},{"code":231,"indent":1,"parameters":[3,"Coelhosis",0,0,430,215,65,65,255,0]},{"code":101,"indent":1,"parameters":["",0,1,2]},{"code":401,"indent":1,"parameters":["\\C[6] Marisol: \\C[0]Pera, \\.como é?"]},{"code":101,"indent":1,"parameters":["",0,1,2]},{"code":401,"indent":1,"parameters":["\\C[6] Marisol: \\C[0]Eu não sou real? \\.hahah"]},{"code":235,"indent":1,"parameters":[3]},{"code":230,"indent":1,"parameters":[20]},{"code":231,"indent":1,"parameters":[3,"Coelhosis",0,0,430,215,65,65,255,0]},{"code":101,"indent":1,"parameters":["",0,1,2]},{"code":401,"indent":1,"parameters":["\\C[6] Marisol: \\C[0]Aquela mãezona aranha te acertou na cabeça, \\.foi?"]},{"code":235,"indent":1,"parameters":[3]},{"code":230,"indent":1,"parameters":[30]},{"code":356,"indent":1,"parameters":["MSGSE TALK DEFAULT"]},{"code":231,"indent":1,"parameters":[2,"Badyuma5",0,0,330,125,80,80,255,0]},{"code":101,"indent":1,"parameters":["",0,1,2]},{"code":401,"indent":1,"parameters":["\\C[8] Yuma: \\C[0]Esse é um daqueles sonhos que você parece acordado."]},{"code":235,"indent":1,"parameters":[2]},{"code":230,"indent":1,"parameters":[20]},{"code":231,"indent":1,"parameters":[2,"Badyuma5",0,0,330,125,80,80,255,0]},{"code":101,"indent":1,"parameters":["",0,1,2]},{"code":401,"indent":1,"parameters":["\\C[8] Yuma: \\C[0]Não lembro o nome..."]},{"code":235,"indent":1,"parameters":[2]},{"code":230,"indent":1,"parameters":[30]},{"code":231,"indent":1,"parameters":[2,"Badyuma5",0,0,330,125,80,80,255,0]},{"code":101,"indent":1,"parameters":["",0,1,2]},{"code":401,"indent":1,"parameters":["\\C[8] Yuma: \\C[0]Ah é, \\.sonho lúcido."]},{"code":235,"indent":1,"parameters":[2]},{"code":230,"indent":1,"parameters":[20]},{"code":231,"indent":1,"parameters":[2,"Badyuma5",0,0,330,125,80,80,255,0]},{"code":101,"indent":1,"parameters":["",0,1,2]},{"code":401,"indent":1,"parameters":["\\C[8] Yuma: \\C[0]Já já eu acordo e tá tudo resolvido."]},{"code":235,"indent":1,"parameters":[2]},{"code":230,"indent":1,"parameters":[60]},{"code":356,"indent":1,"parameters":["MSGSE TALK 3"]},{"code":231,"indent":1,"parameters":[3,"Coelhosis",0,0,430,215,65,65,255,0]},{"code":101,"indent":1,"parameters":["",0,1,2]},{"code":401,"indent":1,"parameters":["\\C[6] Marisol: \\C[0]Você pensa que é um sonho?"]},{"code":235,"indent":1,"parameters":[3]},{"code":230,"indent":1,"parameters":[50]},{"code":231,"indent":1,"parameters":[3,"Coelhosis",0,0,430,215,65,65,255,0]},{"code":101,"indent":1,"parameters":["",0,1,2]},{"code":401,"indent":1,"parameters":["\\C[6] Marisol: \\C[0]Tadinha..."]},{"code":235,"indent":1,"parameters":[3]},{"code":230,"indent":1,"parameters":[30]},{"code":231,"indent":1,"parameters":[3,"Coelhosis",0,0,430,215,65,65,255,0]},{"code":101,"indent":1,"parameters":["",0,1,2]},{"code":401,"indent":1,"parameters":["\\C[6] Marisol: \\C[0]Queria eu que fosse."]},{"code":235,"indent":1,"parameters":[3]},{"code":230,"indent":1,"parameters":[40]},{"code":231,"indent":1,"parameters":[3,"Coelhosis",0,0,430,215,65,65,255,0]},{"code":101,"indent":1,"parameters":["",0,1,2]},{"code":401,"indent":1,"parameters":["\\C[6] Marisol: \\C[0]Mas o buraco é bem mais embaixo..."]},{"code":235,"indent":1,"parameters":[3]},{"code":230,"indent":1,"parameters":[65]},{"code":231,"indent":1,"parameters":[3,"Coelhosis",0,0,430,215,65,65,255,0]},{"code":101,"indent":1,"parameters":["",0,1,2]},{"code":401,"indent":1,"parameters":["\\C[6] Marisol: \\C[0]A gente pode discutir os detalhes depois,"]},{"code":230,"indent":1,"parameters":[20]},{"code":101,"indent":1,"parameters":["",0,1,2]},{"code":401,"indent":1,"parameters":["\\C[6] Marisol: \\C[0]Você precisa vir comigo."]},{"code":235,"indent":1,"parameters":[3]},{"code":230,"indent":1,"parameters":[30]},{"code":231,"indent":1,"parameters":[3,"Coelhosis",0,0,430,215,65,65,255,0]},{"code":101,"indent":1,"parameters":["",0,1,2]},{"code":401,"indent":1,"parameters":["\\C[6] Marisol: \\C[0]Ah menos que queria esperar até a dona aranha voltar."]},{"code":235,"indent":1,"parameters":[3]},{"code":230,"indent":1,"parameters":[30]},{"code":356,"indent":1,"parameters":["MSGSE TALK DEFAULT"]},{"code":231,"indent":1,"parameters":[2,"Badyuma5",0,0,330,125,80,80,255,0]},{"code":101,"indent":1,"parameters":["",0,1,2]},{"code":401,"indent":1,"parameters":["\\C[8] Yuma: \\C[0]..."]},{"code":235,"indent":1,"parameters":[2]},{"code":230,"indent":1,"parameters":[40]},{"code":356,"indent":1,"parameters":["MSGSE TALK 3"]},{"code":231,"indent":1,"parameters":[3,"Coelhosis",0,0,430,215,65,65,255,0]},{"code":101,"indent":1,"parameters":["",0,1,2]},{"code":401,"indent":1,"parameters":["\\C[6] Marisol: \\C[0]Mas você quem sabe né, \\.o sonho é seu."]},{"code":235,"indent":1,"parameters":[3]},{"code":230,"indent":1,"parameters":[60]},{"code":231,"indent":1,"parameters":[1,"Coelhosis",0,0,430,215,65,65,255,0]},{"code":101,"indent":1,"parameters":["",0,1,2]},{"code":401,"indent":1,"parameters":["\\C[6] Marisol: \\C[0]Se mudar de idéia,"]},{"code":101,"indent":1,"parameters":["",0,1,2]},{"code":401,"indent":1,"parameters":["\\C[6] Marisol: \\C[0]A porta tá bem ali."]},{"code":235,"indent":1,"parameters":[1]},{"code":205,"indent":1,"parameters":[-1,{"list":[{"code":41,"parameters":["$Yuma",0],"indent":null},{"code":0}],"repeat":false,"skippable":false,"wait":false}]},{"code":505,"indent":1,"parameters":[{"code":41,"parameters":["$Yuma",0],"indent":null}]},{"code":242,"indent":1,"parameters":[1]},{"code":201,"indent":1,"parameters":[0,127,3,9,8,0]},{"code":205,"indent":1,"parameters":[-1,{"list":[{"code":41,"parameters":["$Yuma",0],"indent":null},{"code":0}],"repeat":false,"skippable":false,"wait":false}]},{"code":505,"indent":1,"parameters":[{"code":41,"parameters":["$Yuma",0],"indent":null}]},{"code":205,"indent":1,"parameters":[2,{"list":[{"code":19,"indent":null},{"code":4,"indent":null},{"code":4,"indent":null},{"code":4,"indent":null},{"code":4,"indent":null},{"code":0}],"repeat":false,"skippable":false,"wait":true}]},{"code":505,"indent":1,"parameters":[{"code":19,"indent":null}]},{"code":505,"indent":1,"parameters":[{"code":4,"indent":null}]},{"code":505,"indent":1,"parameters":[{"code":4,"indent":null}]},{"code":505,"indent":1,"parameters":[{"code":4,"indent":null}]},{"code":505,"indent":1,"parameters":[{"code":4,"indent":null}]},{"code":250,"indent":1,"parameters":[{"name":"tm2_chair003","volume":30,"pitch":100,"pan":0}]},{"code":121,"indent":1,"parameters":[40,40,0]},{"code":221,"indent":1,"parameters":[]},{"code":201,"indent":1,"parameters":[0,127,3,5,8,0]},{"code":356,"indent":1,"parameters":["mv3d camera target ＠player 0"]},{"code":356,"indent":1,"parameters":["show_all_indicators"]},{"code":356,"indent":1,"parameters":["mv3d dist 5 0"]},{"code":222,"indent":1,"parameters":[]},{"code":230,"indent":1,"parameters":[30]},{"code":203,"indent":1,"parameters":[2,0,6,19,0]},{"code":250,"indent":1,"parameters":[{"name":"Close1","volume":20,"pitch":100,"pan":0}]},{"code":230,"indent":1,"parameters":[90]},{"code":356,"indent":1,"parameters":["MSGSE TALK DEFAULT"]},{"code":231,"indent":1,"parameters":[2,"Badyuma5",0,0,330,125,80,80,255,0]},{"code":101,"indent":1,"parameters":["",0,1,2]},{"code":401,"indent":1,"parameters":["\\C[8] Yuma: \\C[0]..."]},{"code":235,"indent":1,"parameters":[2]},{"code":230,"indent":1,"parameters":[30]},{"code":231,"indent":1,"parameters":[2,"Badyuma5",0,0,330,125,80,80,255,0]},{"code":101,"indent":1,"parameters":["",0,1,2]},{"code":401,"indent":1,"parameters":["\\C[8] Yuma: \\C[0]Isso não faz sentido..."]},{"code":235,"indent":1,"parameters":[2]},{"code":230,"indent":1,"parameters":[70]},{"code":231,"indent":1,"parameters":[2,"Badyuma5",0,0,330,125,80,80,255,0]},{"code":101,"indent":1,"parameters":["",0,1,2]},{"code":401,"indent":1,"parameters":["\\C[8] Yuma: \\C[0]Calma Yuma..."]},{"code":235,"indent":1,"parameters":[2]},{"code":230,"indent":1,"parameters":[20]},{"code":231,"indent":1,"parameters":[2,"Badyuma5",0,0,330,125,80,80,255,0]},{"code":101,"indent":1,"parameters":["",0,1,2]},{"code":401,"indent":1,"parameters":["\\C[8] Yuma: \\C[0]Você vai acordar a qualquer instante."]},{"code":101,"indent":1,"parameters":["",0,1,2]},{"code":401,"indent":1,"parameters":["\\C[8] Yuma: \\C[0]Só ta demorando um pouco mais que o normal..."]},{"code":235,"indent":1,"parameters":[2]},{"code":0,"indent":1,"parameters":[]},{"code":412,"indent":0,"parameters":[]},{"code":0,"indent":0,"parameters":[]}],"moveFrequency":3,"moveRoute":{"list":[{"code":0,"parameters":[]}],"repeat":true,"skippable":false,"wait":false},"moveSpeed":3,"moveType":0,"priorityType":0,"stepAnime":false,"through":false,"trigger":1,"walkAnime":true}],"x":4,"y":9},
{"id":12,"name":"EV012","note":"","pages":[{"conditions":{"actorId":1,"actorValid":false,"itemId":1,"itemValid":false,"selfSwitchCh":"A","selfSwitchValid":false,"switch1Id":1,"switch1Valid":false,"switch2Id":1,"switch2Valid":false,"variableId":1,"variableValid":false,"variableValue":0},"directionFix":false,"image":{"tileId":0,"characterName":"","direction":2,"pattern":2,"characterIndex":0},"list":[{"code":0,"indent":0,"parameters":[]}],"moveFrequency":3,"moveRoute":{"list":[{"code":0,"parameters":[]}],"repeat":true,"skippable":false,"wait":false},"moveSpeed":3,"moveType":0,"priorityType":1,"stepAnime":false,"through":false,"trigger":0,"walkAnime":true}],"x":3,"y":8},
{"id":13,"name":"EV013","note":"","pages":[{"conditions":{"actorId":1,"actorValid":false,"itemId":1,"itemValid":false,"selfSwitchCh":"A","selfSwitchValid":false,"switch1Id":1,"switch1Valid":false,"switch2Id":1,"switch2Valid":false,"variableId":1,"variableValid":false,"variableValue":0},"directionFix":false,"image":{"tileId":0,"characterName":"","direction":2,"pattern":2,"characterIndex":0},"list":[{"code":0,"indent":0,"parameters":[]}],"moveFrequency":3,"moveRoute":{"list":[{"code":0,"parameters":[]}],"repeat":true,"skippable":false,"wait":false},"moveSpeed":3,"moveType":0,"priorityType":1,"stepAnime":false,"through":false,"trigger":0,"walkAnime":true}],"x":2,"y":8},
{"id":14,"name":"EV014","note":"<mv3d:shape(fence),z(0),x(-0),y(-0.46),scale(2.2,2.2),rot(180),shadow(false)>","pages":[{"conditions":{"actorId":1,"actorValid":false,"itemId":1,"itemValid":false,"selfSwitchCh":"A","selfSwitchValid":false,"switch1Id":1,"switch1Valid":false,"switch2Id":1,"switch2Valid":false,"variableId":1,"variableValid":false,"variableValue":0},"directionFix":false,"image":{"characterIndex":0,"characterName":"","direction":2,"pattern":0,"tileId":0},"list":[{"code":0,"indent":0,"parameters":[]}],"moveFrequency":3,"moveRoute":{"list":[{"code":0,"parameters":[]}],"repeat":true,"skippable":false,"wait":false},"moveSpeed":3,"moveType":0,"priorityType":0,"stepAnime":false,"through":false,"trigger":0,"walkAnime":true},{"conditions":{"actorId":1,"actorValid":false,"itemId":1,"itemValid":false,"selfSwitchCh":"A","selfSwitchValid":false,"switch1Id":40,"switch1Valid":true,"switch2Id":1,"switch2Valid":false,"variableId":1,"variableValid":false,"variableValue":0},"directionFix":true,"image":{"tileId":0,"characterName":"!$pixi_room","direction":6,"pattern":2,"characterIndex":0},"moveFrequency":3,"moveRoute":{"list":[{"code":0,"indent":null,"parameters":[]}],"repeat":true,"skippable":false,"wait":false},"moveSpeed":3,"moveType":0,"priorityType":0,"stepAnime":false,"through":false,"trigger":0,"walkAnime":false,"list":[{"code":108,"indent":0,"parameters":["<mv3d:"]},{"code":408,"indent":0,"parameters":["lamp(white,1.5,1.1)"]},{"code":408,"indent":0,"parameters":["lampHeight(1)"]},{"code":408,"indent":0,"parameters":[">"]},{"code":111,"indent":0,"parameters":[6,-1,8]},{"code":221,"indent":1,"parameters":[]},{"code":356,"indent":1,"parameters":["MSGSE TALK DEFAULT"]},{"code":242,"indent":1,"parameters":[1]},{"code":250,"indent":1,"parameters":[{"name":"Open5","volume":45,"pitch":100,"pan":0}]},{"code":201,"indent":1,"parameters":[0,1,8,11,0,0]},{"code":205,"indent":1,"parameters":[-1,{"list":[{"code":41,"parameters":["$Yuma",0],"indent":null},{"code":0}],"repeat":false,"skippable":false,"wait":false}]},{"code":505,"indent":1,"parameters":[{"code":41,"parameters":["$Yuma",0],"indent":null}]},{"code":356,"indent":1,"parameters":["eraseFilter oldf oldfilm"]},{"code":356,"indent":1,"parameters":["mv3d ＠player lamp white 0 0 0"]},{"code":356,"indent":1,"parameters":["mv3d ＠player flashlight white 0 0 0 0"]},{"code":356,"indent":1,"parameters":["mv3d cameraMode orthographic"]},{"code":356,"indent":1,"parameters":["mv3d fog black 8 12 0"]},{"code":356,"indent":1,"parameters":["mv3d ambient #1B0A2A 0"]},{"code":356,"indent":1,"parameters":["mv3d sun pitch 30 0"]},{"code":356,"indent":1,"parameters":["mv3d yaw -8 0"]},{"code":356,"indent":1,"parameters":["mv3d dist 7 0"]},{"code":356,"indent":1,"parameters":["mv3d pitch 65 0"]},{"code":223,"indent":1,"parameters":[[-17,-17,17,17],1,false]},{"code":241,"indent":1,"parameters":[{"name":"silence sound effect","volume":15,"pitch":70,"pan":0}]},{"code":250,"indent":1,"parameters":[{"name":"Open4","volume":45,"pitch":100,"pan":0}]},{"code":230,"indent":1,"parameters":[30]},{"code":222,"indent":1,"parameters":[]},{"code":230,"indent":1,"parameters":[60]},{"code":356,"indent":1,"parameters":["MSGSE TALK 3"]},{"code":231,"indent":1,"parameters":[1,"Coelhosis",0,0,430,215,65,65,255,0]},{"code":101,"indent":1,"parameters":["",0,1,2]},{"code":401,"indent":1,"parameters":["\\C[6] Marisol: \\C[0]Ei..."]},{"code":235,"indent":1,"parameters":[1]},{"code":356,"indent":1,"parameters":["mv3d camera target ＠e24 1"]},{"code":230,"indent":1,"parameters":[30]},{"code":231,"indent":1,"parameters":[1,"Coelhosis",0,0,430,215,65,65,255,0]},{"code":101,"indent":1,"parameters":["",0,1,2]},{"code":401,"indent":1,"parameters":["\\C[6] Marisol: \\C[0]Aqui, \\.aqui!"]},{"code":235,"indent":1,"parameters":[1]},{"code":356,"indent":1,"parameters":["MSGSE TALK DEFAULT"]},{"code":356,"indent":1,"parameters":["mv3d camera target ＠player 0"]},{"code":0,"indent":1,"parameters":[]},{"code":412,"indent":0,"parameters":[]},{"code":0,"indent":0,"parameters":[]}]}],"x":3,"y":2},
{"id":15,"name":"EV015","note":"","pages":[{"conditions":{"actorId":1,"actorValid":false,"itemId":1,"itemValid":false,"selfSwitchCh":"A","selfSwitchValid":false,"switch1Id":1,"switch1Valid":false,"switch2Id":1,"switch2Valid":false,"variableId":1,"variableValid":false,"variableValue":0},"directionFix":false,"image":{"tileId":0,"characterName":"","direction":2,"pattern":2,"characterIndex":0},"list":[{"code":0,"indent":0,"parameters":[]}],"moveFrequency":3,"moveRoute":{"list":[{"code":0,"parameters":[]}],"repeat":true,"skippable":false,"wait":false},"moveSpeed":3,"moveType":0,"priorityType":1,"stepAnime":false,"through":false,"trigger":0,"walkAnime":true}],"x":4,"y":8},
{"id":16,"name":"EV016","note":"","pages":[{"conditions":{"actorId":1,"actorValid":false,"itemId":1,"itemValid":false,"selfSwitchCh":"A","selfSwitchValid":false,"switch1Id":1,"switch1Valid":false,"switch2Id":1,"switch2Valid":false,"variableId":1,"variableValid":false,"variableValue":0},"directionFix":false,"image":{"tileId":0,"characterName":"","direction":2,"pattern":0,"characterIndex":0},"moveFrequency":3,"moveRoute":{"list":[{"code":0,"indent":null,"parameters":[]}],"repeat":true,"skippable":false,"wait":false},"moveSpeed":3,"moveType":0,"priorityType":0,"stepAnime":false,"through":false,"trigger":1,"walkAnime":true,"list":[{"code":111,"indent":0,"parameters":[6,-1,2]},{"code":231,"indent":1,"parameters":[1,"Yuma2",0,0,330,125,80,80,255,0]},{"code":101,"indent":1,"parameters":["",0,1,2]},{"code":401,"indent":1,"parameters":["\\C[8] Yuma: \\C[0]Melhor eu seguir ela..."]},{"code":235,"indent":1,"parameters":[1]},{"code":0,"indent":1,"parameters":[]},{"code":412,"indent":0,"parameters":[]},{"code":0,"indent":0,"parameters":[]}]}],"x":2,"y":7},
{"id":17,"name":"EV017","note":"","pages":[{"conditions":{"actorId":1,"actorValid":false,"itemId":1,"itemValid":false,"selfSwitchCh":"A","selfSwitchValid":false,"switch1Id":1,"switch1Valid":false,"switch2Id":1,"switch2Valid":false,"variableId":1,"variableValid":false,"variableValue":0},"directionFix":false,"image":{"tileId":0,"characterName":"","direction":2,"pattern":0,"characterIndex":0},"moveFrequency":3,"moveRoute":{"list":[{"code":0,"indent":null,"parameters":[]}],"repeat":true,"skippable":false,"wait":false},"moveSpeed":3,"moveType":0,"priorityType":0,"stepAnime":false,"through":false,"trigger":1,"walkAnime":true,"list":[{"code":111,"indent":0,"parameters":[6,-1,2]},{"code":231,"indent":1,"parameters":[1,"Yuma2",0,0,330,125,80,80,255,0]},{"code":101,"indent":1,"parameters":["",0,1,2]},{"code":401,"indent":1,"parameters":["\\C[8] Yuma: \\C[0]Melhor eu seguir ela..."]},{"code":235,"indent":1,"parameters":[1]},{"code":0,"indent":1,"parameters":[]},{"code":412,"indent":0,"parameters":[]},{"code":0,"indent":0,"parameters":[]}]}],"x":3,"y":7},
{"id":18,"name":"EV018","note":"","pages":[{"conditions":{"actorId":1,"actorValid":false,"itemId":1,"itemValid":false,"selfSwitchCh":"A","selfSwitchValid":false,"switch1Id":1,"switch1Valid":false,"switch2Id":1,"switch2Valid":false,"variableId":1,"variableValid":false,"variableValue":0},"directionFix":false,"image":{"tileId":0,"characterName":"","direction":2,"pattern":0,"characterIndex":0},"moveFrequency":3,"moveRoute":{"list":[{"code":0,"indent":null,"parameters":[]}],"repeat":true,"skippable":false,"wait":false},"moveSpeed":3,"moveType":0,"priorityType":0,"stepAnime":false,"through":false,"trigger":1,"walkAnime":true,"list":[{"code":111,"indent":0,"parameters":[6,-1,2]},{"code":231,"indent":1,"parameters":[1,"Yuma2",0,0,330,125,80,80,255,0]},{"code":101,"indent":1,"parameters":["",0,1,2]},{"code":401,"indent":1,"parameters":["\\C[8] Yuma: \\C[0]Melhor eu seguir ela..."]},{"code":235,"indent":1,"parameters":[1]},{"code":0,"indent":1,"parameters":[]},{"code":412,"indent":0,"parameters":[]},{"code":0,"indent":0,"parameters":[]}]}],"x":4,"y":7},
null,
null,
null,
null,
null,
null,
null,
null,
null,
null,
null,
null,
null,
null,
null,
null,
null,
{"id":36,"name":"EV036","note":"","pages":[{"conditions":{"actorId":1,"actorValid":false,"itemId":1,"itemValid":false,"selfSwitchCh":"A","selfSwitchValid":false,"switch1Id":1,"switch1Valid":false,"switch2Id":1,"switch2Valid":false,"variableId":1,"variableValid":false,"variableValue":0},"directionFix":false,"image":{"characterIndex":0,"characterName":"","direction":2,"pattern":0,"tileId":0},"list":[{"code":355,"indent":0,"parameters":[" $gameScreen.startShake(0.8, 0.3, 1); "]},{"code":0,"indent":0,"parameters":[]}],"moveFrequency":3,"moveRoute":{"list":[{"code":0,"parameters":[]}],"repeat":true,"skippable":false,"wait":false},"moveSpeed":3,"moveType":0,"priorityType":0,"stepAnime":false,"through":false,"trigger":4,"walkAnime":true}],"x":6,"y":19},
null,
null,
null,
null,
null,
null,
null,
null,
null,
{"id":46,"name":"EV046","note":"","pages":[{"conditions":{"actorId":1,"actorValid":false,"itemId":1,"itemValid":false,"selfSwitchCh":"A","selfSwitchValid":false,"switch1Id":1,"switch1Valid":false,"switch2Id":1,"switch2Valid":false,"variableId":1,"variableValid":false,"variableValue":0},"directionFix":false,"image":{"characterIndex":0,"characterName":"","direction":2,"pattern":0,"tileId":0},"list":[{"code":205,"indent":0,"parameters":[-1,{"list":[{"code":41,"parameters":["$Yuma",0],"indent":null},{"code":0}],"repeat":false,"skippable":false,"wait":true}]},{"code":505,"indent":0,"parameters":[{"code":41,"parameters":["$Yuma",0],"indent":null}]},{"code":0,"indent":0,"parameters":[]}],"moveFrequency":3,"moveRoute":{"list":[{"code":0,"parameters":[]}],"repeat":true,"skippable":false,"wait":false},"moveSpeed":3,"moveType":0,"priorityType":0,"stepAnime":false,"through":false,"trigger":4,"walkAnime":true}],"x":0,"y":0},
null,
null,
null,
null,
null,
null,
null,
null,
null,
null,
null,
null,
null,
null,
null,
null,
null,
null,
null,
null,
null,
null,
null,
null,
null,
null,
null,
null,
null,
null,
null
]
}